label_tools/label_merge_branches/cli.py
label_tools/labelme_stats/cli.py
label_tools-1.0.3.data/scripts/label-assign-task
label_tools-1.0.3.data/scripts/label-assign-task-batch
label_tools-1.0.3.data/scripts/label-clone-repo
label_tools-1.0.3.data/scripts/label-pull-task
label_tools-1.0.3.data/scripts/label-push-task
label_tools-1.0.3.data/scripts/label-reassign-task
label_tools-1.0.3.dist-info/METADATA
label_tools-1.0.3.dist-info/WHEEL
label_tools-1.0.3.dist-info/entry_points.txt
label_tools-1.0.3.dist-info/top_level.txt
label_tools-1.0.3.dist-info/RECORD
