Metadata-Version: 2.1
Name: label_tools
Version: 1.0.3
Summary: Label Tools
Author-email: Bryt <bryt.xin.li@gmail.com>
Project-URL: Homepage, https://github.com/xin-at-marathon/pypi
Project-URL: Issues, https://github.com/xin-at-marathon/pypi/issues
Classifier: Programming Language :: Python :: 3
Classifier: License :: OSI Approved :: MIT License
Classifier: Operating System :: OS Independent
Requires-Python: >=3.6
